[
  {
    "date": "2023-11-30",
    "referent": "Sebastien Fournaise",
    "authCode": "8923476198",
    "question1": "Orléans - Rédeau TAO",
    "question2": "TOKTOK",
    "questions": [
        {"code": "La vie est belle", "alreadyFound": false},
        {"code": "Maman, j'ai rate l'avion", "alreadyFound": false},
        {"code": "Le Grinch", "alreadyFound": false},
        {"code": "Love Actually", "alreadyFound": false},
        {"code": "Miracle sur la 34e rue", "alreadyFound": false},
        {"code": "L'étrange Noël de monsieur Jack", "alreadyFound": false},
        {"code": "Elfe", "alreadyFound": false},
        {"code": "Une merveilleuse vie", "alreadyFound": false},
        {"code": "Le Pole Express", "alreadyFound": false},
        {"code": "Noel chez les Muppets", "alreadyFound": false}
      ]
    },
    {
      "date": "2023-12-01",
      "referent": "Test",
      "authCode": "8923476198",
      "question1": "",
      "question2": "",
      "questions": [
        
      ]
    },
    {
      "date": "2023-12-04",
      "referent": "Lucas Dragone",
      "authCode": "4567891230",
      "question1": "",
      "question2": "",
      "questions": [
        {"code": "La vie est belle", "alreadyFound": false},
        {"code": "Maman, j'ai rate l'avion", "alreadyFound": false},
        {"code": "Le Grinch", "alreadyFound": false},
        {"code": "Love Actually", "alreadyFound": false},
        {"code": "Miracle sur la 34e rue", "alreadyFound": false},
        {"code": "L'étrange Noël de monsieur Jack", "alreadyFound": false},
        {"code": "Elfe", "alreadyFound": false},
        {"code": "Une merveilleuse vie", "alreadyFound": false},
        {"code": "Le Pole Express", "alreadyFound": false},
        {"code": "Noel chez les Muppets", "alreadyFound": false},
        {"code": "Maman, j'ai encore rate l'avion", "alreadyFound": false},
        {"code": "L'amour de l'or", "alreadyFound": false},
        {"code": "L'etoile de Noel", "alreadyFound": false},
        {"code": "Gremlins", "alreadyFound": false},
        {"code": "L'arnaque de Noel", "alreadyFound": false},
        {"code": "Noel blanc", "alreadyFound": false},
        {"code": "Bad Santa", "alreadyFound": false},
        {"code": "La course au jouet", "alreadyFound": false},
        {"code": "Les vacances de Noel", "alreadyFound": false},
        {"code": "Le sapin a les boules", "alreadyFound": false}
      ]
    },
    {
      "date": "2023-12-05",
      "referent": "Sebastien Fournaise",
      "authCode": "7012345678",
      "question1": "",
      "question2": "",
      "questions": [
        {"code": "L'etrange Noel de Scrooge", "alreadyFound": false},
        {"code": "Comment le Grinch a vole Noel", "alreadyFound": false},
        {"code": "Un Noel de folie", "alreadyFound": false},
        {"code": "Noel chez les Coopers", "alreadyFound": false},
        {"code": "Super Noel", "alreadyFound": false},
        {"code": "Un conte de Noel", "alreadyFound": false},
        {"code": "Un prince pour Noel", "alreadyFound": false},
        {"code": "Noel mortel", "alreadyFound": false},
        {"code": "Le sapin de Noel", "alreadyFound": false},
        {"code": "Le Noel de Mickey", "alreadyFound": false},
        {"code":"L'envol des anges", "alreadyFound":false},
        {"code":"La symphonie des etoiles", "alreadyFound":false},
        {"code":"Les voeux exauces de Noel", "alreadyFound":false},
        {"code":"La magie des flocons", "alreadyFound":false},
        {"code":"Le rêve de Noel", "alreadyFound":false},
        {"code":"L'etoile qui guide Noel", "alreadyFound":false},
        {"code":"La fête des etoiles filantes", "alreadyFound":false},
        {"code":"La danse des lumieres de Noel", "alreadyFound":false},
        {"code":"L'eclat des etoiles brillantes", "alreadyFound":false},
        {"code":"Le secret du Pere Noel", "alreadyFound":false}
      ]
    },
    {
      "date": "2023-12-06",
      "referent": "Calypso Legrand",
      "authCode": "8234567891",
      "question1": "",
      "question2": "",
      "questions": [
        {"code":"L'amour ne s'achete pas", "alreadyFound":false},
        {"code":"Le Grinch (2000)", "alreadyFound":false},
        {"code":"La magie de Noel", "alreadyFound":false},
        {"code":"Noel au soleil", "alreadyFound":false},
        {"code":"Joyeux Noel", "alreadyFound":false},
        {"code":"Un Noel tout en douceur", "alreadyFound":false},
        {"code":"L'etoile de Noel (2017)", "alreadyFound":false},
        {"code":"Noel avec les voisins", "alreadyFound":false},
        {"code":"Les chroniques de Noel", "alreadyFound":false},
        {"code":"Un rêve de Noel", "alreadyFound":false},
        {"code":"L'eclat des etoiles de Noel", "alreadyFound":false},
        {"code":"La feerie des lumieres", "alreadyFound":false},
        {"code":"Les rires de Noel", "alreadyFound":false},
        {"code":"L'harmonie du reveillon", "alreadyFound":false},
        {"code":"Les etoiles magiques", "alreadyFound":false},
        {"code":"Le miracle de decembre", "alreadyFound":false},
        {"code":"Les voeux eternels", "alreadyFound":false},
        {"code":"La magie des cadeaux", "alreadyFound":false}
      ]
    },
    {
      "date": "2023-12-07",
      "referent": "Sebastien Fournaise",
      "authCode": "9870123456",
      "question1": "",
      "question2": "",
      "questions": [
        {"code":"Le sapin a des boules", "alreadyFound":false},
        {"code":"Les lutins", "alreadyFound":false},
        {"code":"Noel en heritage", "alreadyFound":false},
        {"code":"La course au cadeau", "alreadyFound":false},
        {"code":"Une journee de folie", "alreadyFound":false},
        {"code":"L'amour de Noel", "alreadyFound":false},
        {"code":"Les Rois du desert", "alreadyFound":false},
        {"code":"Noel au bout des doigts", "alreadyFound":false},
        {"code":"Miracle sur la 5e avenue", "alreadyFound":false},
        {"code":"Jack Frost", "alreadyFound":false},
        {"code":"Les etoiles eblouissantes de Noel", "alreadyFound":false},
        {"code":"Le charme intemporel du reveillon", "alreadyFound":false},
        {"code":"La symphonie des etoiles filantes", "alreadyFound":false},
        {"code":"Le miracle des fêtes", "alreadyFound":false},
        {"code":"L'eclat du sapin de Noel", "alreadyFound":false},
        {"code":"Les voeux exauces de decembre", "alreadyFound":false},
        {"code":"Le tourbillon enchante de Noel", "alreadyFound":false},
        {"code":"Les rêves illumines de decembre", "alreadyFound":false},
        {"code":"La magie des etoiles scintillantes", "alreadyFound":false},
        {"code":"L'etoile qui danse a Noel", "alreadyFound":false}
      ]
    },
    {
      "date": "2023-12-08",
      "referent": "Mathieu Roy",
      "authCode": "2345678901",
      "question1": "",
      "question2": "",
      "questions": [
        {"code":"Un Noel de princesse", "alreadyFound": false},
        {"code":"Le cadeau de la vie", "alreadyFound": false},
        {"code":"Noel en famille", "alreadyFound": false},
        {"code":"La magie de Noel (2007)", "alreadyFound": false},
        {"code":"Un Noel a la maison", "alreadyFound": false},
        {"code":"Les etoiles de Noel", "alreadyFound": false},
        {"code":"Une seconde chance pour Noel", "alreadyFound": false},
        {"code":"La fête de Noel", "alreadyFound": false},
        {"code":"Les deux font la paire", "alreadyFound": false},
        {"code":"Noel en plein ete", "alreadyFound": false},
        {"code":"Le bal des etoiles de Noel", "alreadyFound":false},
        {"code":"La feerie du reveillon", "alreadyFound":false},
        {"code":"Les etoiles eclatantes de decembre", "alreadyFound":false},
        {"code":"L'eclat des guirlandes magiques", "alreadyFound":false},
        {"code":"La symphonie des etoiles dorees", "alreadyFound":false},
        {"code":"La magie des rires de Noel", "alreadyFound":false},
        {"code":"Le charme hivernal de decembre", "alreadyFound":false},
        {"code":"Les voeux etincelants de Noel", "alreadyFound":false}
      ]
    },
    {
      "date": "2023-12-11",
      "referent": "Anais Remy",
      "authCode": "1098765432",
      "question1": "",
      "question2": "",
      "questions": [
        {"code":"L'esprit de Noel", "alreadyFound":false},
        {"code":"La magie de la famille", "alreadyFound":false},
        {"code":"La liste de Noel", "alreadyFound":false},
        {"code":"Une merveilleuse fête d'hiver", "alreadyFound":false},
        {"code":"Noel au coin du feu", "alreadyFound":false},
        {"code":"Un Noel enchante", "alreadyFound":false},
        {"code":"Un Noel pour l'eternite", "alreadyFound":false},
        {"code":"Noel entre amis", "alreadyFound":false},
        {"code":"La belle et la bûche", "alreadyFound":false},
        {"code":"Le miracle de Noel", "alreadyFound":false},
        {"code":"La danse des étoiles brillantes", "alreadyFound": false},
        {"code":"Les lumières du réveillon", "alreadyFound": false},
        {"code":"L'éclat des étoiles de décembre", "alreadyFound": false},
        {"code":"Le charme féerique de Noël", "alreadyFound": false},
        {"code":"La symphonie magique des fêtes", "alreadyFound": false},
        {"code":"Les voeux étincelants de décembre", "alreadyFound": false},
        {"code":"Le rêve des étoiles scintillantes", "alreadyFound": false},
        {"code":"Les éclats de rire de Noël", "alreadyFound": false}
      ]
    },
    {
      "date": "2023-12-12",
      "referent": "Sebastien Fournaise",
      "authCode": "3456789012",
      "question1": "",
      "question2": "",
      "questions": [
        {"code":"Les contes de Noel", "alreadyFound":false},
        {"code":"L'eclat de Noel", "alreadyFound":false},
        {"code":"Un Noel inoubliable", "alreadyFound":false},
        {"code":"La fête de fin d'annee", "alreadyFound":false},
        {"code":"Noel a la campagne", "alreadyFound":false},
        {"code":"L'arbre de Noel", "alreadyFound":false},
        {"code":"La cle du bonheur", "alreadyFound":false},
        {"code":"Un Noel en famille (2015)", "alreadyFound":false},
        {"code":"L'etincelle de Noel", "alreadyFound":false},
        {"code":"Un amour de Noel", "alreadyFound":false},
        {"code":"Le bal féerique de Noël", "alreadyFound":false},
        {"code":"Les lumières éclatantes du réveillon", "alreadyFound":false},
        {"code":"La magie des étoiles de décembre", "alreadyFound":false},
        {"code":"L'éclat du charme hivernal", "alreadyFound":false},
        {"code":"Le tourbillon enchanté des fêtes", "alreadyFound":false},
        {"code":"Les voeux scintillants de Noël", "alreadyFound":false},
        {"code":"La danse des étoiles magiques", "alreadyFound":false},
        {"code":"L'éclat du rire de Noël", "alreadyFound":false}
      ]
    },
    {
      "date": "2023-12-13",
      "referent": "Calypso Legrand",
      "authCode": "5678901234",
      "question1": "",
      "question2": "",
      "questions": [
        {"code":"Noel a New York", "alreadyFound": false},
        {"code":"Le charme de Noel", "alreadyFound": false},
        {"code":"Les joyeux lurons de Noel", "alreadyFound": false},
        {"code":"La magie des fêtes", "alreadyFound": false},
        {"code":"Noel au grand cœur", "alreadyFound": false},
        {"code":"L'etoile du berger", "alreadyFound": false},
        {"code":"Les anges de Noel", "alreadyFound": false},
        {"code":"Un Noel enchantant", "alreadyFound": false},
        {"code":"Le sapin de l'espoir", "alreadyFound": false},
        {"code":"Le prince de Noel", "alreadyFound": false},
        {"code":"La féerie des étoiles dorées", "alreadyFound":false},
        {"code":"Les lumières éclatantes du sapin de Noël", "alreadyFound":false},
        {"code":"Le charme magique du réveillon", "alreadyFound":false},
        {"code":"L'éclat des étoiles scintillantes de décembre", "alreadyFound":false},
        {"code":"La danse féerique des flocons de neige", "alreadyFound":false},
        {"code":"Le tourbillon étincelant de Noël", "alreadyFound":false},
        {"code":"Les voeux éternels de décembre", "alreadyFound":false},
        {"code":"L'éclat du rire enchanté de Noël", "alreadyFound":false}
      ]
    },
    {
      "date": "2023-12-14",
      "referent": "Sebastien Fournaise",
      "authCode": "8901234567",
      "question1": "",
      "question2": "",
      "questions": [
        {"code":"Noel en musique","alreadyFound": false},
        {"code":"La magie des etoiles","alreadyFound": false},
        {"code":"Le cadeau de Noel","alreadyFound": false},
        {"code":"Les rêves de Noel","alreadyFound": false},
        {"code":"Un Noel feerique","alreadyFound": false},
        {"code":"La valse des flocons","alreadyFound": false},
        {"code":"Noel au clair de lune","alreadyFound": false},
        {"code":"Le secret de Noel","alreadyFound": false},
        {"code":"L'esprit festif","alreadyFound": false},
        {"code":"Le ballet de Noel","alreadyFound": false},
        {"code":"Le bal enchante des etoiles filantes", "alreadyFound":false},
        {"code":"Les lumières eblouissantes du reveillon de Noël", "alreadyFound":false},
        {"code":"La magie des etoiles dorees de decembre", "alreadyFound":false},
        {"code":"L'eclat du charme festif", "alreadyFound":false},
        {"code":"Le tourbillon enchante des lumières de Noël", "alreadyFound":false},
        {"code":"Les voeux scintillants de decembre", "alreadyFound":false},
        {"code":"La danse feerique des etoiles magiques", "alreadyFound":false},
        {"code":"L'eclat du rire festif de Noël", "alreadyFound":false}
      ]
    },
    {
      "date": "2023-12-15",
      "referent": "Mathieu Roy",
      "authCode": "6789012345",
      "question1": "",
      "question2": "",
      "questions": [
        {"code":"La magie des rennes","alreadyFound":false},
        {"code":"Les etoiles filantes de Noel","alreadyFound":false},
        {"code":"Un Noel de rêve","alreadyFound":false},
        {"code":"Noel dans les montagnes","alreadyFound":false},
        {"code":"L'atelier du Pere Noel","alreadyFound":false},
        {"code":"La feerie de Noel","alreadyFound":false},
        {"code":"Les lumieres de Noel","alreadyFound":false},
        {"code":"La neige et l'amour de Noel","alreadyFound":false},
        {"code":"La melodie de Noel","alreadyFound":false},
        {"code":"Le voyage de Noel","alreadyFound":false},
        {"code":"Les étoiles enchantées du réveillon", "alreadyFound": false},
        {"code":"Le bal féerique des étoiles éclatantes", "alreadyFound": false},
        {"code":"La magie des flocons de neige", "alreadyFound": false},
        {"code":"L'éclat du charme hivernal de Noël", "alreadyFound": false},
        {"code":"Le tourbillon enchanté des fêtes de fin d'année", "alreadyFound": false},
        {"code":"Les voeux éternels de décembre", "alreadyFound": false},
        {"code":"La danse des étoiles scintillantes", "alreadyFound": false},
        {"code":"L'éclat du rire festif de Noël", "alreadyFound": false}
      ]
    },
    {
      "date": "2023-12-18",
      "referent": "Layriane Jedynak",
      "authCode": "3210987654",
      "question1": "",
      "question2": "",
      "questions": [
        {"code":"La danse des flocons", "alreadyFound":false},
        {"code":"Noel en harmonie", "alreadyFound":false},
        {"code":"Le chant de Noel", "alreadyFound":false},
        {"code":"Les eclats de rire de Noel", "alreadyFound":false},
        {"code":"Un Noel eblouissant", "alreadyFound":false},
        {"code":"Le miracle de l'hiver", "alreadyFound":false},
        {"code":"Les promesses de Noel", "alreadyFound":false},
        {"code":"La symphonie des fêtes", "alreadyFound":false},
        {"code":"L'etoile brillante de Noel", "alreadyFound":false},
        {"code":"Les voeux de Noel", "alreadyFound":false},
        {"code":"La magie des étoiles éclatantes","alreadyFound":false},
        {"code":"Le bal féerique du réveillon","alreadyFound":false},
        {"code":"L'éclat du charme festif de Noël","alreadyFound":false},
        {"code":"Le tourbillon enchanté des lumières de décembre","alreadyFound":false},
        {"code":"Les voeux étincelants de Noël","alreadyFound":false},
        {"code":"La danse des étoiles dorées","alreadyFound":false},
        {"code":"L'éclat du rire enchanteur de Noël","alreadyFound":false},
        {"code":"La symphonie féerique des flocons de neige","alreadyFound":false}
      ]
    },
    {
      "date": "2023-12-19",
      "referent": "Sebastien Fournaise",
      "authCode": "5432109876",
      "question1": "",
      "question2": "",
      "questions": [
        {"code":"Noel au clair de lune", "alreadyFound":false},
        {"code":"La magie des etoiles filantes", "alreadyFound":false},
        {"code":"Les voeux de Noel exauces", "alreadyFound":false},
        {"code":"Le ballet feerique de Noel", "alreadyFound":false},
        {"code":"L'eclat du sapin", "alreadyFound":false},
        {"code":"La feerie de Noel", "alreadyFound":false},
        {"code":"Les anges chantent a Noel", "alreadyFound":false},
        {"code":"Le joyeux tourbillon de Noel", "alreadyFound":false},
        {"code":"La danse des rennes", "alreadyFound":false},
        {"code":"Le charme intemporel de Noel", "alreadyFound":false},
        {"code":"Le bal des étoiles enchantées", "alreadyFound":false},
        {"code":"Les lumières festives du réveillon", "alreadyFound":false},
        {"code":"La magie des étoiles scintillantes de Noël", "alreadyFound":false},
        {"code":"L'éclat du charme hivernal", "alreadyFound":false},
        {"code":"Le tourbillon enchanteur des fêtes de fin d'année", "alreadyFound":false},
        {"code":"Les voeux éternels de décembre", "alreadyFound":false},
        {"code":"La danse des étoiles dorées", "alreadyFound":false},
        {"code":"L'éclat du rire festif de Noël", "alreadyFound":false}
      ]
    },
    {
      "date": "2023-12-20",
      "referent": "Bastien Metreau",
      "authCode": "8765432109",
      "question1": "",
      "question2": "",
      "questions": [
        {"code":"Noel sous les etoiles", "alreadyFound":false},
        {"code":"La magie du reveillon", "alreadyFound":false},
        {"code":"Les feux de Noel", "alreadyFound":false},
        {"code":"L'eclat des guirlandes", "alreadyFound":false},
        {"code":"La feerie hivernale", "alreadyFound":false},
        {"code":"Les flocons enchantes", "alreadyFound":false},
        {"code":"La symphonie de Noel", "alreadyFound":false},
        {"code":"Les voix de Noel", "alreadyFound":false},
        {"code":"Les etoiles scintillantes", "alreadyFound":false},
        {"code":"L'eclat des bougies de Noel", "alreadyFound":false},
        {"code":"La féerie des étoiles éclatantes", "alreadyFound":false},
        {"code":"Le bal enchanté du réveillon", "alreadyFound":false},
        {"code":"L'éclat du charme festif de Noël", "alreadyFound":false},
        {"code":"Le tourbillon des lumières de décembre", "alreadyFound":false},
        {"code":"Les voeux scintillants de Noël", "alreadyFound":false},
        {"code":"La danse des étoiles dorées", "alreadyFound":false},
        {"code":"L'éclat du rire enchanteur de Noël", "alreadyFound":false},
        {"code":"La symphonie féerique des flocons de neige", "alreadyFound":false}
      ]
    }
  ]
  